Workbook

Sheet Diluted Shares
A1: PALISADE BIO (PALI) — Fully Diluted Share Count
A2: Based on public disclosures through Dec 2025 + estimated future dilution
A4: Security Type | B4: Shares | C4: Ex. Price ($) | D4: Source / Notes
A5: Common Shares Outstanding (Basic) | B5: 149003210 | D5: Source: StockAnalysis/InvestorsHub, record date Oct 17, 2025
A7: WARRANTS
A8: Oct 2025 Offering Overallotment (fully exercised) | B8: 25714285 | C8: 0.7 | D8: Oct 2025 $138M offering; full overallotment
A9: Replacement Warrants (July 2025 inducement) | B9: 8637810 | C9: 0.9047 | D9: July 2025 warrant exercise; SH approval Dec 2025
A10: Placement Agent Warrants (est.) | B10: 5000000 | C10: 0.7 | D10: Est. from Oct 2025 offering placement agent
A11: Legacy / Other Warrants (est.) | B11: 3000000 | C11: 1.4 | D11: Remaining older warrants from prior financings
A12: Total Warrants | B12: =SUM(B8:B11) -> 42352095
A14: STOCK OPTIONS & RSUs
A15: 2021 Equity Incentive Plan Options (est.) | B15: 2500000 | C15: 1.5 | D15: Mix of exercise prices; est. from 10-K filings
A16: 2021 Inducement Plan Options (est.) | B16: 1500000 | C16: 1.2 | D16: Inducement grants to new executives
A17: RSUs / Restricted Stock Awards (est.) | B17: 500000 | C17: 0 | D17: Est. unvested RSUs
A18: Total Options & RSUs | B18: =SUM(B15:B17) -> 4500000
A20: ESTIMATED FUTURE DILUTION
A21: Future equity raise for Phase 3 funding (est.) | B21: 9230769 | C21: 6.5 | D21: Assumption: ~$60M raise at ~$6.50/share Phase 3 funding event (2028)
A22: Total Future Dilution | B22: =B21 -> 9230769
A24: FULLY DILUTED SHARE COUNT | B24: =B5+B12+B18+B22 -> 205086074 | D24: Basic + Warrants + Options/RSUs + Future Raises

Sheet rNPV Model
A1: PALISADE BIO (PALI) — Risk-Adjusted Net Present Value (rNPV)
A2: Lead Asset: PALI-2108 (oral gut-targeted PDE4 B/D inhibitor) | UC & FSCD | Feb 2026
A4: KEY ASSUMPTIONS
A5: Discount Rate (WACC) | B5: 0.13 | C5: Typical early-stage biotech WACC - PoC & safety proven in UC phase 1a
A6: Tax Rate | B6: 0.21 | C6: US Federal corporate rate
A7: Patent Expiry Year | B7: 2041 | C7: Canadian patent through May 2041
A8: Launch Year — UC | B8: 2031 | C8: Ph2 2027-28, Ph3 2028-30, approval ~2031
A9: Launch Year — FSCD | B9: 2032 | C9: Ph2 2028-29, Ph3 2029-31, approval ~2032
A10: Model Base Year | B10: 2026 | C10: NPV calculated from 2026
A12: INDICATION 1: ULCERATIVE COLITIS (UC)
A13: UC TAM at Launch ($M) | B13: 10000 | C13: Global UC market ~$8-10B by 2031 (multiple sources)
A14: Peak Market Share (%) | B14: 0.06 | C14: oral PDE4 in crowded biologics market
A15: Peak Annual Revenue ($M) | B15: =B13*B14 -> 600 | C15: →tam × Share
A16: Net Profit Margin (after COGS, SGA, R&D, tax) | B16: 0.35 | C16: 85% GM - 30% SGA - 10% R&D, ×(1-21% tax)
A17: Peak Net Income ($M) | B17: =B15*B16 -> 210 | C17: →peak rev × Net Margin
A18: Ramp Adjustment Factor | B18: 0.6 | C18: Avg NI as % of peak over patent life (ramp up/down)
A20: UC — Phase Transition Probabilities
A21: Phase 1b → Phase 2 | B21: 0.9 | C21: 100% clinical response in Ph1b = near-certain to advance
A22: Phase 2 → Phase 3 | B22: 0.5 | C22: Strong Ph1 signal carries; oral convenience vs biologics
A23: Phase 3 → NDA Filing | B23: 0.7 | C23: If Ph2 confirms, high confidence in Ph3
A24: NDA → FDA Approval | B24: 0.9 | C24: Oral, clean safety profile supports favorable NDA review
A25: Cumulative PoS (cPoS) | B25: =B21*B22*B23*B24 -> 0.2835 | C25: →product of all phases
A27: INDICATION 2: FIBROSTENOTIC CROHN'S DISEASE (FSCD)
A28: FSCD Target Patient Population (US) | B28: 300000 | C28: Est. ~150K Symptomatic/Active FSCD patients & ~150k Post-op maintenance; ZERO approved therapies
A29: Annual Revenue per Patient ($) | B29: 40000 | C29: Estimated specialty oral drug annual cost
A30: US Peak Market Penetration (%) | B30: 0.15 | C30: first & only therapy; strong first-mover; blending symptomatic/Active penetration (20%) with Post-op maintenance penetration (10%)
A31: Peak US Revenue ($M) | B31: =B28*B29*B30/1000000 -> 1800 | C31: →patients × Rev/pt × Penetration
A32: ROW Multiplier | B32: 0.5 | C32: ROW revenue = 50% of US
A33: Total Peak Revenue ($M) | B33: =B31*(1+B32) -> 2700 | C33: →us × (1+ROW)
A34: Net Profit Margin (%) | B34: 0.35 | C34: Similar margin profile as UC
A35: Peak Net Income ($M) | B35: =B33*B34 -> 945 | C35: →peak rev × Margin
A36: Ramp Adjustment Factor | B36: 0.65 | C36: Faster ramp — first & only therapy
A38: FSCD — Phase Transition Probabilities
A39: Phase 1b → Phase 2 | B39: 0.8 | C39: UC safety de-risks; PDE4B antifibrotic validated in IPF (NEJM)
A40: Phase 2 → Phase 3 | B40: 0.4 | C40: Agomab STENOVA de-risks FSCD regulatory path; dual MOA
A41: Phase 3 → NDA Filing | B41: 0.65 | C41: Breakthrough Therapy likely; STAR consortium endpoints
A42: NDA → FDA Approval | B42: 0.85 | C42: Zero approved therapies; massive unmet need
A43: Cumulative PoS (cPoS) | B43: =B39*B40*B41*B42 -> 0.1768 | C43: →product of all phases
A45: rNPV CALCULATION
A46: UC PROGRAM
A47: Commercial life (yrs) | B47: =B7-B8 -> 10 | C47: 2041 patent − 2031 launch
A48: Peak annual revenue ($M) | B48: =B15 -> 600 | C48: TAM × peak share
A49: Peak net income ($M) | B49: =B17 -> 210 | C49: Peak rev × 35% margin
A50: Avg net income ($M, ramp-adjusted) | B50: =B17*B18 -> 126 | C50: Peak NI × 60% ramp factor
A51: PV of income stream at launch ($M) | B51: =B50*((1-(1+B5)^(-B47))/B5) -> 683.70668 | C51: Annuity PV over commercial life
A52: PV discounted to 2026 ($M) | B52: =B51/(1+B5)^(B8-B10) -> 371.08859 | C52: Discount 5 yrs to base year
A53: Cumulative PoS | B53: =B25 -> 0.2835
A54: UC Risk-Adjusted Revenue NPV ($M) | B54: =B52*B53 -> 105.20362
A56: FSCD PROGRAM
A57: Commercial life (yrs) | B57: =B7-B9 -> 9 | C57: 2041 patent − 2032 launch
A58: Peak annual revenue ($M) | B58: =B33 -> 2700 | C58: $810M peak (US+ROW)
A59: Peak net income ($M) | B59: =B35 -> 945 | C59: Peak rev × 35% margin
A60: Avg net income ($M, ramp-adjusted) | B60: =B35*B36 -> 614.25 | C60: Peak NI × 65% ramp factor
A61: PV of income stream at launch ($M) | B61: =B60*((1-(1+B5)^(-B57))/B5) -> 3152.1192 | C61: Annuity PV
A62: PV discounted to 2026 ($M) | B62: =B61/(1+B5)^(B9-B10) -> 1514.0212 | C62: Discount 6 yrs
A63: Cumulative PoS | B63: =B43 -> 0.1768
A64: FSCD Risk-Adjusted Revenue NPV ($M) | B64: =B62*B63 -> 267.67895
A66: RISK-ADJUSTED DEVELOPMENT COSTS
A67: UC Phase 2 ($M, committed) | B67: -25 | C67: Oral small molecule, CRO-run, large registrational study planned N=195
A68: UC Phase 3 ($M, × P(reach Ph3)) | B68: =-55*B21*B22 -> -24.75 | C68: $55M × P(Ph1b→Ph2) × P(Ph2→Ph3)
A69: FSCD Phase 2 ($M, committed) | B69: -12 | C69: Smaller cohort
A70: FSCD Phase 3 ($M, × P(reach Ph3)) | B70: =-40*B39*B40 -> -12.8 | C70: $40M × P(Ph1b→Ph2) × P(Ph2→Ph3)
A71: G&A to commercialization ($M) | B71: -42 | C71: ~$6M/yr 2026-2027 (Phase 2) + ~10M/yr 2028-2030 (Phase 3 & NDA)
A72: PV of total dev costs ($M) | B72: =(B67+B68+B69+B70+B71)/(1+B5)^2.5 -> -85.864999 | C72: Discounted at ~2.5yr midpoint
A74: TOTAL Risk-Adj Pipeline Revenue ($M) | B74: =B54+B64 -> 372.88257
A75: PV of Development Costs ($M) | B75: =B72 -> -85.864999
A76: NET PIPELINE rNPV ($M) | B76: =B74+B75 -> 287.01757 | C76: Revenue minus dev costs
A78: STRATEGIC & OPTION VALUE
A79: Partnership / M&A premium (25%) | B79: =MAX(0,B76)*0.25 -> 71.754393 | C79: 25% — oral dual-mechanism, IP to 2041, validated PDE4B target
A80: Platform / preclinical optionality ($M) | B80: 50 | C80: PDE4 platform, gut restricted platform
A82: CASH POSITION
A83: Cash & equivalents ($M) | B83: 205.5 | C83: Post Oct 2025 raise ($138M gross) + projected $60M future raise + $15.5M warrants
A84: Debt ($M) | B84: -5
A85: Net cash ($M) | B85: =B83+B84 -> 200.5 | C85: NO burn deduct — already in dev costs
A87: TOTAL EQUITY rNPV ($M) | B87: =B76+B79+B80+B85 -> 609.27196 | C87: Pipeline + strategic + cash
A89: FAIR VALUE PER SHARE
A90: Fully Diluted Shares | B90: ='Diluted Shares'!B24 -> 205086074
A91: rNPV FAIR VALUE PER SHARE ($) | B91: =B87*1000000/B90 -> 2.970811
A93: Current Stock Price ($) | B93: 1.74
A94: Upside / (Downside) | B94: =(B91-B93)/B93 -> 0.70736264
A96: Clear Street Price Target ($) | B96: 12 | C96: Source: Clear Street initiation Dec 2025, Buy
A98: VALUE BRIDGE ($/share)
A99: Net Cash / Share | B99: =B85*1000000/B90 -> 0.9776383 | C99: Cash floor
A100: + Net Pipeline Value / Share | B100: =B76*1000000/B90 -> 1.3994981 | C100: Risk-adj pipeline net of dev costs
A101: + Strategic Premium / Share | B101: =(B79+B80)*1000000/B90 -> 0.5936746 | C101: M&A + optionality
A102: FAIR VALUE / SHARE | B102: =B91 -> 2.970811

Sheet Sensitivity
A1: PALI rNPV — SENSITIVITY ANALYSIS
A3: Reference Values (linked to rNPV Model)
A4: WACC | B4: ='rNPV Model'!B5 -> 0.13 | C4: UC Market Share | D4: ='rNPV Model'!B14 -> 0.06
A5: UC cPoS | B5: ='rNPV Model'!B25 -> 0.2835 | C5: FSCD cPoS | D5: ='rNPV Model'!B43 -> 0.1768
A6: Fully Diluted Shares | B6: ='rNPV Model'!B90 -> 205086074 | C6: Net Cash ($M) | D6: ='rNPV Model'!B85 -> 200.5
A7: Platform Optionality ($M) | B7: ='rNPV Model'!B80 -> 50 | C7: M&A Premium | D7: =0.25 -> 0.25
A8: Base Fair Value | B8: ='rNPV Model'!B91 -> 2.970811 | C8: Current Price | D8: ='rNPV Model'!B93 -> 1.74
A10: Fair Value by UC Market Share & WACC
A11: WACC \ UC Share | B11: 0.02 | C11: 0.04 | D11: 0.06 | E11: 0.08 | F11: 0.1
A12: 0.11 | B12: =(((((('rNPV Model'!B13*B$11*'rNPV Model'!B16*'rNPV Model'!B18)*((1-(1+$A12)^(-'rNPV Model'!B47))/$A12))/(1+$A12)^('rNPV Model'!B8-'rNPV Model'!B10))*'rNPV Model'!B25)+((('rNPV Model'!B60*((1-(1+$A12)^(-'rNPV Model'!B57))/$A12))/(1+$A12)^('rNPV Model'!B9-'rNPV Model'!B10))*'rNPV Model'!B43)+(('rNPV Model'!B67+'rNPV Model'!B68+'rNPV Model'!B69+'rNPV Model'!B70+'rNPV Model'!B71)/(1+$A12)^2.5))+MAX(0,((((('rNPV Model'!B13*B$11*'rNPV Model'!B16*'rNPV Model'!B18)*((1-(1+$A12)^(-'rNPV Model'!B47))/$A12))/(1+$A12)^('rNPV Model'!B8-'rNPV Model'!B10))*'rNPV Model'!B25)+((('rNPV Model'!B60*((1-(1+$A12)^(-'rNPV Model'!B57))/$A12))/(1+$A12)^('rNPV Model'!B9-'rNPV Model'!B10))*'rNPV Model'!B43)+(('rNPV Model'!B67+'rNPV Model'!B68+'rNPV Model'!B69+'rNPV Model'!B70+'rNPV Model'!B71)/(1+$A12)^2.5)))*$D$7+'rNPV Model'!B80+'rNPV Model'!B85)*1000000/'rNPV Model'!B90 -> 2.8873223 | C12: =(((((('rNPV Model'!B13*C$11*'rNPV Model'!B16*'rNPV Model'!B18)*((1-(1+$A12)^(-'rNPV Model'!B47))/$A12))/(1+$A12)^('rNPV Model'!B8-'rNPV Model'!B10))*'rNPV Model'!B25)+((('rNPV Model'!B60*((1-(1+$A12)^(-'rNPV Model'!B57))/$A12))/(1+$A12)^('rNPV Model'!B9-'rNPV Model'!B10))*'rNPV Model'!B43)+(('rNPV Model'!B67+'rNPV Model'!B68+'rNPV Model'!B69+'rNPV Model'!B70+'rNPV Model'!B71)/(1+$A12)^2.5))+MAX(0,((((('rNPV Model'!B13*C$11*'rNPV Model'!B16*'rNPV Model'!B18)*((1-(1+$A12)^(-'rNPV Model'!B47))/$A12))/(1+$A12)^('rNPV Model'!B8-'rNPV Model'!B10))*'rNPV Model'!B25)+((('rNPV Model'!B60*((1-(1+$A12)^(-'rNPV Model'!B57))/$A12))/(1+$A12)^('rNPV Model'!B9-'rNPV Model'!B10))*'rNPV Model'!B43)+(('rNPV Model'!B67+'rNPV Model'!B68+'rNPV Model'!B69+'rNPV Model'!B70+'rNPV Model'!B71)/(1+$A12)^2.5)))*$D$7+'rNPV Model'!B80+'rNPV Model'!B85)*1000000/'rNPV Model'!B90 -> 3.1409636 | D12: =(((((('rNPV Model'!B13*D$11*'rNPV Model'!B16*'rNPV Model'!B18)*((1-(1+$A12)^(-'rNPV Model'!B47))/$A12))/(1+$A12)^('rNPV Model'!B8-'rNPV Model'!B10))*'rNPV Model'!B25)+((('rNPV Model'!B60*((1-(1+$A12)^(-'rNPV Model'!B57))/$A12))/(1+$A12)^('rNPV Model'!B9-'rNPV Model'!B10))*'rNPV Model'!B43)+(('rNPV Model'!B67+'rNPV Model'!B68+'rNPV Model'!B69+'rNPV Model'!B70+'rNPV Model'!B71)/(1+$A12)^2.5))+MAX(0,((((('rNPV Model'!B13*D$11*'rNPV Model'!B16*'rNPV Model'!B18)*((1-(1+$A12)^(-'rNPV Model'!B47))/$A12))/(1+$A12)^('rNPV Model'!B8-'rNPV Model'!B10))*'rNPV Model'!B25)+((('rNPV Model'!B60*((1-(1+$A12)^(-'rNPV Model'!B57))/$A12))/(1+$A12)^('rNPV Model'!B9-'rNPV Model'!B10))*'rNPV Model'!B43)+(('rNPV Model'!B67+'rNPV Model'!B68+'rNPV Model'!B69+'rNPV Model'!B70+'rNPV Model'!B71)/(1+$A12)^2.5)))*$D$7+'rNPV Model'!B80+'rNPV Model'!B85)*1000000/'rNPV Model'!B90 -> 3.3946049 | E12: =(((((('rNPV Model'!B13*E$11*'rNPV Model'!B16*'rNPV Model'!B18)*((1-(1+$A12)^(-'rNPV Model'!B47))/$A12))/(1+$A12)^('rNPV Model'!B8-'rNPV Model'!B10))*'rNPV Model'!B25)+((('rNPV Model'!B60*((1-(1+$A12)^(-'rNPV Model'!B57))/$A12))/(1+$A12)^('rNPV Model'!B9-'rNPV Model'!B10))*'rNPV Model'!B43)+(('rNPV Model'!B67+'rNPV Model'!B68+'rNPV Model'!B69+'rNPV Model'!B70+'rNPV Model'!B71)/(1+$A12)^2.5))+MAX(0,((((('rNPV Model'!B13*E$11*'rNPV Model'!B16*'rNPV Model'!B18)*((1-(1+$A12)^(-'rNPV Model'!B47))/$A12))/(1+$A12)^('rNPV Model'!B8-'rNPV Model'!B10))*'rNPV Model'!B25)+((('rNPV Model'!B60*((1-(1+$A12)^(-'rNPV Model'!B57))/$A12))/(1+$A12)^('rNPV Model'!B9-'rNPV Model'!B10))*'rNPV Model'!B43)+(('rNPV Model'!B67+'rNPV Model'!B68+'rNPV Model'!B69+'rNPV Model'!B70+'rNPV Model'!B71)/(1+$A12)^2.5)))*$D$7+'rNPV Model'!B80+'rNPV Model'!B85)*1000000/'rNPV Model'!B90 -> 3.6482462 | F12: =(((((('rNPV Model'!B13*F$11*'rNPV Model'!B16*'rNPV Model'!B18)*((1-(1+$A12)^(-'rNPV Model'!B47))/$A12))/(1+$A12)^('rNPV Model'!B8-'rNPV Model'!B10))*'rNPV Model'!B25)+((('rNPV Model'!B60*((1-(1+$A12)^(-'rNPV Model'!B57))/$A12))/(1+$A12)^('rNPV Model'!B9-'rNPV Model'!B10))*'rNPV Model'!B43)+(('rNPV Model'!B67+'rNPV Model'!B68+'rNPV Model'!B69+'rNPV Model'!B70+'rNPV Model'!B71)/(1+$A12)^2.5))+MAX(0,((((('rNPV Model'!B13*F$11*'rNPV Model'!B16*'rNPV Model'!B18)*((1-(1+$A12)^(-'rNPV Model'!B47))/$A12))/(1+$A12)^('rNPV Model'!B8-'rNPV Model'!B10))*'rNPV Model'!B25)+((('rNPV Model'!B60*((1-(1+$A12)^(-'rNPV Model'!B57))/$A12))/(1+$A12)^('rNPV Model'!B9-'rNPV Model'!B10))*'rNPV Model'!B43)+(('rNPV Model'!B67+'rNPV Model'!B68+'rNPV Model'!B69+'rNPV Model'!B70+'rNPV Model'!B71)/(1+$A12)^2.5)))*$D$7+'rNPV Model'!B80+'rNPV Model'!B85)*1000000/'rNPV Model'!B90 -> 3.9018875
A13: 0.12 | B13: =(((((('rNPV Model'!B13*B$11*'rNPV Model'!B16*'rNPV Model'!B18)*((1-(1+$A13)^(-'rNPV Model'!B47))/$A13))/(1+$A13)^('rNPV Model'!B8-'rNPV Model'!B10))*'rNPV Model'!B25)+((('rNPV Model'!B60*((1-(1+$A13)^(-'rNPV Model'!B57))/$A13))/(1+$A13)^('rNPV Model'!B9-'rNPV Model'!B10))*'rNPV Model'!B43)+(('rNPV Model'!B67+'rNPV Model'!B68+'rNPV Model'!B69+'rNPV Model'!B70+'rNPV Model'!B71)/(1+$A13)^2.5))+MAX(0,((((('rNPV Model'!B13*B$11*'rNPV Model'!B16*'rNPV Model'!B18)*((1-(1+$A13)^(-'rNPV Model'!B47))/$A13))/(1+$A13)^('rNPV Model'!B8-'rNPV Model'!B10))*'rNPV Model'!B25)+((('rNPV Model'!B60*((1-(1+$A13)^(-'rNPV Model'!B57))/$A13))/(1+$A13)^('rNPV Model'!B9-'rNPV Model'!B10))*'rNPV Model'!B43)+(('rNPV Model'!B67+'rNPV Model'!B68+'rNPV Model'!B69+'rNPV Model'!B70+'rNPV Model'!B71)/(1+$A13)^2.5)))*$D$7+'rNPV Model'!B80+'rNPV Model'!B85)*1000000/'rNPV Model'!B90 -> 2.7058141 | C13: =(((((('rNPV Model'!B13*C$11*'rNPV Model'!B16*'rNPV Model'!B18)*((1-(1+$A13)^(-'rNPV Model'!B47))/$A13))/(1+$A13)^('rNPV Model'!B8-'rNPV Model'!B10))*'rNPV Model'!B25)+((('rNPV Model'!B60*((1-(1+$A13)^(-'rNPV Model'!B57))/$A13))/(1+$A13)^('rNPV Model'!B9-'rNPV Model'!B10))*'rNPV Model'!B43)+(('rNPV Model'!B67+'rNPV Model'!B68+'rNPV Model'!B69+'rNPV Model'!B70+'rNPV Model'!B71)/(1+$A13)^2.5))+MAX(0,((((('rNPV Model'!B13*C$11*'rNPV Model'!B16*'rNPV Model'!B18)*((1-(1+$A13)^(-'rNPV Model'!B47))/$A13))/(1+$A13)^('rNPV Model'!B8-'rNPV Model'!B10))*'rNPV Model'!B25)+((('rNPV Model'!B60*((1-(1+$A13)^(-'rNPV Model'!B57))/$A13))/(1+$A13)^('rNPV Model'!B9-'rNPV Model'!B10))*'rNPV Model'!B43)+(('rNPV Model'!B67+'rNPV Model'!B68+'rNPV Model'!B69+'rNPV Model'!B70+'rNPV Model'!B71)/(1+$A13)^2.5)))*$D$7+'rNPV Model'!B80+'rNPV Model'!B85)*1000000/'rNPV Model'!B90 -> 2.9384902 | D13: =(((((('rNPV Model'!B13*D$11*'rNPV Model'!B16*'rNPV Model'!B18)*((1-(1+$A13)^(-'rNPV Model'!B47))/$A13))/(1+$A13)^('rNPV Model'!B8-'rNPV Model'!B10))*'rNPV Model'!B25)+((('rNPV Model'!B60*((1-(1+$A13)^(-'rNPV Model'!B57))/$A13))/(1+$A13)^('rNPV Model'!B9-'rNPV Model'!B10))*'rNPV Model'!B43)+(('rNPV Model'!B67+'rNPV Model'!B68+'rNPV Model'!B69+'rNPV Model'!B70+'rNPV Model'!B71)/(1+$A13)^2.5))+MAX(0,((((('rNPV Model'!B13*D$11*'rNPV Model'!B16*'rNPV Model'!B18)*((1-(1+$A13)^(-'rNPV Model'!B47))/$A13))/(1+$A13)^('rNPV Model'!B8-'rNPV Model'!B10))*'rNPV Model'!B25)+((('rNPV Model'!B60*((1-(1+$A13)^(-'rNPV Model'!B57))/$A13))/(1+$A13)^('rNPV Model'!B9-'rNPV Model'!B10))*'rNPV Model'!B43)+(('rNPV Model'!B67+'rNPV Model'!B68+'rNPV Model'!B69+'rNPV Model'!B70+'rNPV Model'!B71)/(1+$A13)^2.5)))*$D$7+'rNPV Model'!B80+'rNPV Model'!B85)*1000000/'rNPV Model'!B90 -> 3.1711662 | E13: =(((((('rNPV Model'!B13*E$11*'rNPV Model'!B16*'rNPV Model'!B18)*((1-(1+$A13)^(-'rNPV Model'!B47))/$A13))/(1+$A13)^('rNPV Model'!B8-'rNPV Model'!B10))*'rNPV Model'!B25)+((('rNPV Model'!B60*((1-(1+$A13)^(-'rNPV Model'!B57))/$A13))/(1+$A13)^('rNPV Model'!B9-'rNPV Model'!B10))*'rNPV Model'!B43)+(('rNPV Model'!B67+'rNPV Model'!B68+'rNPV Model'!B69+'rNPV Model'!B70+'rNPV Model'!B71)/(1+$A13)^2.5))+MAX(0,((((('rNPV Model'!B13*E$11*'rNPV Model'!B16*'rNPV Model'!B18)*((1-(1+$A13)^(-'rNPV Model'!B47))/$A13))/(1+$A13)^('rNPV Model'!B8-'rNPV Model'!B10))*'rNPV Model'!B25)+((('rNPV Model'!B60*((1-(1+$A13)^(-'rNPV Model'!B57))/$A13))/(1+$A13)^('rNPV Model'!B9-'rNPV Model'!B10))*'rNPV Model'!B43)+(('rNPV Model'!B67+'rNPV Model'!B68+'rNPV Model'!B69+'rNPV Model'!B70+'rNPV Model'!B71)/(1+$A13)^2.5)))*$D$7+'rNPV Model'!B80+'rNPV Model'!B85)*1000000/'rNPV Model'!B90 -> 3.4038423 | F13: =(((((('rNPV Model'!B13*F$11*'rNPV Model'!B16*'rNPV Model'!B18)*((1-(1+$A13)^(-'rNPV Model'!B47))/$A13))/(1+$A13)^('rNPV Model'!B8-'rNPV Model'!B10))*'rNPV Model'!B25)+((('rNPV Model'!B60*((1-(1+$A13)^(-'rNPV Model'!B57))/$A13))/(1+$A13)^('rNPV Model'!B9-'rNPV Model'!B10))*'rNPV Model'!B43)+(('rNPV Model'!B67+'rNPV Model'!B68+'rNPV Model'!B69+'rNPV Model'!B70+'rNPV Model'!B71)/(1+$A13)^2.5))+MAX(0,((((('rNPV Model'!B13*F$11*'rNPV Model'!B16*'rNPV Model'!B18)*((1-(1+$A13)^(-'rNPV Model'!B47))/$A13))/(1+$A13)^('rNPV Model'!B8-'rNPV Model'!B10))*'rNPV Model'!B25)+((('rNPV Model'!B60*((1-(1+$A13)^(-'rNPV Model'!B57))/$A13))/(1+$A13)^('rNPV Model'!B9-'rNPV Model'!B10))*'rNPV Model'!B43)+(('rNPV Model'!B67+'rNPV Model'!B68+'rNPV Model'!B69+'rNPV Model'!B70+'rNPV Model'!B71)/(1+$A13)^2.5)))*$D$7+'rNPV Model'!B80+'rNPV Model'!B85)*1000000/'rNPV Model'!B90 -> 3.6365183
A14: 0.13 | B14: =(((((('rNPV Model'!B13*B$11*'rNPV Model'!B16*'rNPV Model'!B18)*((1-(1+$A14)^(-'rNPV Model'!B47))/$A14))/(1+$A14)^('rNPV Model'!B8-'rNPV Model'!B10))*'rNPV Model'!B25)+((('rNPV Model'!B60*((1-(1+$A14)^(-'rNPV Model'!B57))/$A14))/(1+$A14)^('rNPV Model'!B9-'rNPV Model'!B10))*'rNPV Model'!B43)+(('rNPV Model'!B67+'rNPV Model'!B68+'rNPV Model'!B69+'rNPV Model'!B70+'rNPV Model'!B71)/(1+$A14)^2.5))+MAX(0,((((('rNPV Model'!B13*B$11*'rNPV Model'!B16*'rNPV Model'!B18)*((1-(1+$A14)^(-'rNPV Model'!B47))/$A14))/(1+$A14)^('rNPV Model'!B8-'rNPV Model'!B10))*'rNPV Model'!B25)+((('rNPV Model'!B60*((1-(1+$A14)^(-'rNPV Model'!B57))/$A14))/(1+$A14)^('rNPV Model'!B9-'rNPV Model'!B10))*'rNPV Model'!B43)+(('rNPV Model'!B67+'rNPV Model'!B68+'rNPV Model'!B69+'rNPV Model'!B70+'rNPV Model'!B71)/(1+$A14)^2.5)))*$D$7+'rNPV Model'!B80+'rNPV Model'!B85)*1000000/'rNPV Model'!B90 -> 2.5433335 | C14: =(((((('rNPV Model'!B13*C$11*'rNPV Model'!B16*'rNPV Model'!B18)*((1-(1+$A14)^(-'rNPV Model'!B47))/$A14))/(1+$A14)^('rNPV Model'!B8-'rNPV Model'!B10))*'rNPV Model'!B25)+((('rNPV Model'!B60*((1-(1+$A14)^(-'rNPV Model'!B57))/$A14))/(1+$A14)^('rNPV Model'!B9-'rNPV Model'!B10))*'rNPV Model'!B43)+(('rNPV Model'!B67+'rNPV Model'!B68+'rNPV Model'!B69+'rNPV Model'!B70+'rNPV Model'!B71)/(1+$A14)^2.5))+MAX(0,((((('rNPV Model'!B13*C$11*'rNPV Model'!B16*'rNPV Model'!B18)*((1-(1+$A14)^(-'rNPV Model'!B47))/$A14))/(1+$A14)^('rNPV Model'!B8-'rNPV Model'!B10))*'rNPV Model'!B25)+((('rNPV Model'!B60*((1-(1+$A14)^(-'rNPV Model'!B57))/$A14))/(1+$A14)^('rNPV Model'!B9-'rNPV Model'!B10))*'rNPV Model'!B43)+(('rNPV Model'!B67+'rNPV Model'!B68+'rNPV Model'!B69+'rNPV Model'!B70+'rNPV Model'!B71)/(1+$A14)^2.5)))*$D$7+'rNPV Model'!B80+'rNPV Model'!B85)*1000000/'rNPV Model'!B90 -> 2.7570723 | D14: =(((((('rNPV Model'!B13*D$11*'rNPV Model'!B16*'rNPV Model'!B18)*((1-(1+$A14)^(-'rNPV Model'!B47))/$A14))/(1+$A14)^('rNPV Model'!B8-'rNPV Model'!B10))*'rNPV Model'!B25)+((('rNPV Model'!B60*((1-(1+$A14)^(-'rNPV Model'!B57))/$A14))/(1+$A14)^('rNPV Model'!B9-'rNPV Model'!B10))*'rNPV Model'!B43)+(('rNPV Model'!B67+'rNPV Model'!B68+'rNPV Model'!B69+'rNPV Model'!B70+'rNPV Model'!B71)/(1+$A14)^2.5))+MAX(0,((((('rNPV Model'!B13*D$11*'rNPV Model'!B16*'rNPV Model'!B18)*((1-(1+$A14)^(-'rNPV Model'!B47))/$A14))/(1+$A14)^('rNPV Model'!B8-'rNPV Model'!B10))*'rNPV Model'!B25)+((('rNPV Model'!B60*((1-(1+$A14)^(-'rNPV Model'!B57))/$A14))/(1+$A14)^('rNPV Model'!B9-'rNPV Model'!B10))*'rNPV Model'!B43)+(('rNPV Model'!B67+'rNPV Model'!B68+'rNPV Model'!B69+'rNPV Model'!B70+'rNPV Model'!B71)/(1+$A14)^2.5)))*$D$7+'rNPV Model'!B80+'rNPV Model'!B85)*1000000/'rNPV Model'!B90 -> 2.970811 | E14: =(((((('rNPV Model'!B13*E$11*'rNPV Model'!B16*'rNPV Model'!B18)*((1-(1+$A14)^(-'rNPV Model'!B47))/$A14))/(1+$A14)^('rNPV Model'!B8-'rNPV Model'!B10))*'rNPV Model'!B25)+((('rNPV Model'!B60*((1-(1+$A14)^(-'rNPV Model'!B57))/$A14))/(1+$A14)^('rNPV Model'!B9-'rNPV Model'!B10))*'rNPV Model'!B43)+(('rNPV Model'!B67+'rNPV Model'!B68+'rNPV Model'!B69+'rNPV Model'!B70+'rNPV Model'!B71)/(1+$A14)^2.5))+MAX(0,((((('rNPV Model'!B13*E$11*'rNPV Model'!B16*'rNPV Model'!B18)*((1-(1+$A14)^(-'rNPV Model'!B47))/$A14))/(1+$A14)^('rNPV Model'!B8-'rNPV Model'!B10))*'rNPV Model'!B25)+((('rNPV Model'!B60*((1-(1+$A14)^(-'rNPV Model'!B57))/$A14))/(1+$A14)^('rNPV Model'!B9-'rNPV Model'!B10))*'rNPV Model'!B43)+(('rNPV Model'!B67+'rNPV Model'!B68+'rNPV Model'!B69+'rNPV Model'!B70+'rNPV Model'!B71)/(1+$A14)^2.5)))*$D$7+'rNPV Model'!B80+'rNPV Model'!B85)*1000000/'rNPV Model'!B90 -> 3.1845497 | F14: =(((((('rNPV Model'!B13*F$11*'rNPV Model'!B16*'rNPV Model'!B18)*((1-(1+$A14)^(-'rNPV Model'!B47))/$A14))/(1+$A14)^('rNPV Model'!B8-'rNPV Model'!B10))*'rNPV Model'!B25)+((('rNPV Model'!B60*((1-(1+$A14)^(-'rNPV Model'!B57))/$A14))/(1+$A14)^('rNPV Model'!B9-'rNPV Model'!B10))*'rNPV Model'!B43)+(('rNPV Model'!B67+'rNPV Model'!B68+'rNPV Model'!B69+'rNPV Model'!B70+'rNPV Model'!B71)/(1+$A14)^2.5))+MAX(0,((((('rNPV Model'!B13*F$11*'rNPV Model'!B16*'rNPV Model'!B18)*((1-(1+$A14)^(-'rNPV Model'!B47))/$A14))/(1+$A14)^('rNPV Model'!B8-'rNPV Model'!B10))*'rNPV Model'!B25)+((('rNPV Model'!B60*((1-(1+$A14)^(-'rNPV Model'!B57))/$A14))/(1+$A14)^('rNPV Model'!B9-'rNPV Model'!B10))*'rNPV Model'!B43)+(('rNPV Model'!B67+'rNPV Model'!B68+'rNPV Model'!B69+'rNPV Model'!B70+'rNPV Model'!B71)/(1+$A14)^2.5)))*$D$7+'rNPV Model'!B80+'rNPV Model'!B85)*1000000/'rNPV Model'!B90 -> 3.3982885
A15: 0.14 | B15: =(((((('rNPV Model'!B13*B$11*'rNPV Model'!B16*'rNPV Model'!B18)*((1-(1+$A15)^(-'rNPV Model'!B47))/$A15))/(1+$A15)^('rNPV Model'!B8-'rNPV Model'!B10))*'rNPV Model'!B25)+((('rNPV Model'!B60*((1-(1+$A15)^(-'rNPV Model'!B57))/$A15))/(1+$A15)^('rNPV Model'!B9-'rNPV Model'!B10))*'rNPV Model'!B43)+(('rNPV Model'!B67+'rNPV Model'!B68+'rNPV Model'!B69+'rNPV Model'!B70+'rNPV Model'!B71)/(1+$A15)^2.5))+MAX(0,((((('rNPV Model'!B13*B$11*'rNPV Model'!B16*'rNPV Model'!B18)*((1-(1+$A15)^(-'rNPV Model'!B47))/$A15))/(1+$A15)^('rNPV Model'!B8-'rNPV Model'!B10))*'rNPV Model'!B25)+((('rNPV Model'!B60*((1-(1+$A15)^(-'rNPV Model'!B57))/$A15))/(1+$A15)^('rNPV Model'!B9-'rNPV Model'!B10))*'rNPV Model'!B43)+(('rNPV Model'!B67+'rNPV Model'!B68+'rNPV Model'!B69+'rNPV Model'!B70+'rNPV Model'!B71)/(1+$A15)^2.5)))*$D$7+'rNPV Model'!B80+'rNPV Model'!B85)*1000000/'rNPV Model'!B90 -> 2.3977221 | C15: =(((((('rNPV Model'!B13*C$11*'rNPV Model'!B16*'rNPV Model'!B18)*((1-(1+$A15)^(-'rNPV Model'!B47))/$A15))/(1+$A15)^('rNPV Model'!B8-'rNPV Model'!B10))*'rNPV Model'!B25)+((('rNPV Model'!B60*((1-(1+$A15)^(-'rNPV Model'!B57))/$A15))/(1+$A15)^('rNPV Model'!B9-'rNPV Model'!B10))*'rNPV Model'!B43)+(('rNPV Model'!B67+'rNPV Model'!B68+'rNPV Model'!B69+'rNPV Model'!B70+'rNPV Model'!B71)/(1+$A15)^2.5))+MAX(0,((((('rNPV Model'!B13*C$11*'rNPV Model'!B16*'rNPV Model'!B18)*((1-(1+$A15)^(-'rNPV Model'!B47))/$A15))/(1+$A15)^('rNPV Model'!B8-'rNPV Model'!B10))*'rNPV Model'!B25)+((('rNPV Model'!B60*((1-(1+$A15)^(-'rNPV Model'!B57))/$A15))/(1+$A15)^('rNPV Model'!B9-'rNPV Model'!B10))*'rNPV Model'!B43)+(('rNPV Model'!B67+'rNPV Model'!B68+'rNPV Model'!B69+'rNPV Model'!B70+'rNPV Model'!B71)/(1+$A15)^2.5)))*$D$7+'rNPV Model'!B80+'rNPV Model'!B85)*1000000/'rNPV Model'!B90 -> 2.5943292 | D15: =(((((('rNPV Model'!B13*D$11*'rNPV Model'!B16*'rNPV Model'!B18)*((1-(1+$A15)^(-'rNPV Model'!B47))/$A15))/(1+$A15)^('rNPV Model'!B8-'rNPV Model'!B10))*'rNPV Model'!B25)+((('rNPV Model'!B60*((1-(1+$A15)^(-'rNPV Model'!B57))/$A15))/(1+$A15)^('rNPV Model'!B9-'rNPV Model'!B10))*'rNPV Model'!B43)+(('rNPV Model'!B67+'rNPV Model'!B68+'rNPV Model'!B69+'rNPV Model'!B70+'rNPV Model'!B71)/(1+$A15)^2.5))+MAX(0,((((('rNPV Model'!B13*D$11*'rNPV Model'!B16*'rNPV Model'!B18)*((1-(1+$A15)^(-'rNPV Model'!B47))/$A15))/(1+$A15)^('rNPV Model'!B8-'rNPV Model'!B10))*'rNPV Model'!B25)+((('rNPV Model'!B60*((1-(1+$A15)^(-'rNPV Model'!B57))/$A15))/(1+$A15)^('rNPV Model'!B9-'rNPV Model'!B10))*'rNPV Model'!B43)+(('rNPV Model'!B67+'rNPV Model'!B68+'rNPV Model'!B69+'rNPV Model'!B70+'rNPV Model'!B71)/(1+$A15)^2.5)))*$D$7+'rNPV Model'!B80+'rNPV Model'!B85)*1000000/'rNPV Model'!B90 -> 2.7909363 | E15: =(((((('rNPV Model'!B13*E$11*'rNPV Model'!B16*'rNPV Model'!B18)*((1-(1+$A15)^(-'rNPV Model'!B47))/$A15))/(1+$A15)^('rNPV Model'!B8-'rNPV Model'!B10))*'rNPV Model'!B25)+((('rNPV Model'!B60*((1-(1+$A15)^(-'rNPV Model'!B57))/$A15))/(1+$A15)^('rNPV Model'!B9-'rNPV Model'!B10))*'rNPV Model'!B43)+(('rNPV Model'!B67+'rNPV Model'!B68+'rNPV Model'!B69+'rNPV Model'!B70+'rNPV Model'!B71)/(1+$A15)^2.5))+MAX(0,((((('rNPV Model'!B13*E$11*'rNPV Model'!B16*'rNPV Model'!B18)*((1-(1+$A15)^(-'rNPV Model'!B47))/$A15))/(1+$A15)^('rNPV Model'!B8-'rNPV Model'!B10))*'rNPV Model'!B25)+((('rNPV Model'!B60*((1-(1+$A15)^(-'rNPV Model'!B57))/$A15))/(1+$A15)^('rNPV Model'!B9-'rNPV Model'!B10))*'rNPV Model'!B43)+(('rNPV Model'!B67+'rNPV Model'!B68+'rNPV Model'!B69+'rNPV Model'!B70+'rNPV Model'!B71)/(1+$A15)^2.5)))*$D$7+'rNPV Model'!B80+'rNPV Model'!B85)*1000000/'rNPV Model'!B90 -> 2.9875434 | F15: =(((((('rNPV Model'!B13*F$11*'rNPV Model'!B16*'rNPV Model'!B18)*((1-(1+$A15)^(-'rNPV Model'!B47))/$A15))/(1+$A15)^('rNPV Model'!B8-'rNPV Model'!B10))*'rNPV Model'!B25)+((('rNPV Model'!B60*((1-(1+$A15)^(-'rNPV Model'!B57))/$A15))/(1+$A15)^('rNPV Model'!B9-'rNPV Model'!B10))*'rNPV Model'!B43)+(('rNPV Model'!B67+'rNPV Model'!B68+'rNPV Model'!B69+'rNPV Model'!B70+'rNPV Model'!B71)/(1+$A15)^2.5))+MAX(0,((((('rNPV Model'!B13*F$11*'rNPV Model'!B16*'rNPV Model'!B18)*((1-(1+$A15)^(-'rNPV Model'!B47))/$A15))/(1+$A15)^('rNPV Model'!B8-'rNPV Model'!B10))*'rNPV Model'!B25)+((('rNPV Model'!B60*((1-(1+$A15)^(-'rNPV Model'!B57))/$A15))/(1+$A15)^('rNPV Model'!B9-'rNPV Model'!B10))*'rNPV Model'!B43)+(('rNPV Model'!B67+'rNPV Model'!B68+'rNPV Model'!B69+'rNPV Model'!B70+'rNPV Model'!B71)/(1+$A15)^2.5)))*$D$7+'rNPV Model'!B80+'rNPV Model'!B85)*1000000/'rNPV Model'!B90 -> 3.1841504
A18: SCENARIO ANALYSIS
A19: Scenario | B19: UC Share | C19: UC cPoS | D19: FSCD cPoS | E19: Platform ($M) | F19: WACC | G19: Fair Value | H19: Notes
A20: Bear Case | B20: 0.02 | C20: 0.161 | D20: 0 | E20: 20 | F20: 0.14 | G20: =((('rNPV Model'!B13*B20*'rNPV Model'!B16*'rNPV Model'!B18*((1-(1+F20)^(-'rNPV Model'!B47))/F20)/(1+F20)^('rNPV Model'!B8-'rNPV Model'!B10)*C20)+('rNPV Model'!B60*((1-(1+F20)^(-'rNPV Model'!B57))/F20)/(1+F20)^('rNPV Model'!B9-'rNPV Model'!B10)*D20)+(('rNPV Model'!B67+'rNPV Model'!B68+'rNPV Model'!B69+'rNPV Model'!B70+'rNPV Model'!B71)/(1+F20)^2.5))+MAX(0,(('rNPV Model'!B13*B20*'rNPV Model'!B16*'rNPV Model'!B18*((1-(1+F20)^(-'rNPV Model'!B47))/F20)/(1+F20)^('rNPV Model'!B8-'rNPV Model'!B10)*C20)+('rNPV Model'!B60*((1-(1+F20)^(-'rNPV Model'!B57))/F20)/(1+F20)^('rNPV Model'!B9-'rNPV Model'!B10)*D20)+(('rNPV Model'!B67+'rNPV Model'!B68+'rNPV Model'!B69+'rNPV Model'!B70+'rNPV Model'!B71)/(1+F20)^2.5)))*$D$7+E20+'rNPV Model'!B85)*1000000/'rNPV Model'!B90 -> 0.7549244 | H20: Zero fibrosis signals, FSCD discontinued, and UC becomes a commercial flop (immediate cash value is still $0.98)
A21: Base Case | B21: ='rNPV Model'!B14 -> 0.06 | C21: ='rNPV Model'!B25 -> 0.2835 | D21: ='rNPV Model'!B43 -> 0.1768 | E21: 50 | F21: ='rNPV Model'!B5 -> 0.13 | G21: =((('rNPV Model'!B13*B21*'rNPV Model'!B16*'rNPV Model'!B18*((1-(1+F21)^(-'rNPV Model'!B47))/F21)/(1+F21)^('rNPV Model'!B8-'rNPV Model'!B10)*C21)+('rNPV Model'!B60*((1-(1+F21)^(-'rNPV Model'!B57))/F21)/(1+F21)^('rNPV Model'!B9-'rNPV Model'!B10)*D21)+(('rNPV Model'!B67+'rNPV Model'!B68+'rNPV Model'!B69+'rNPV Model'!B70+'rNPV Model'!B71)/(1+F21)^2.5))+MAX(0,(('rNPV Model'!B13*B21*'rNPV Model'!B16*'rNPV Model'!B18*((1-(1+F21)^(-'rNPV Model'!B47))/F21)/(1+F21)^('rNPV Model'!B8-'rNPV Model'!B10)*C21)+('rNPV Model'!B60*((1-(1+F21)^(-'rNPV Model'!B57))/F21)/(1+F21)^('rNPV Model'!B9-'rNPV Model'!B10)*D21)+(('rNPV Model'!B67+'rNPV Model'!B68+'rNPV Model'!B69+'rNPV Model'!B70+'rNPV Model'!B71)/(1+F21)^2.5)))*$D$7+E21+'rNPV Model'!B85)*1000000/'rNPV Model'!B90 -> 2.970811
A22: Good (Safety) | B22: 0.06 | C22: 0.32 | D22: 0.221 | E22: 75 | F22: 0.13 | G22: =((('rNPV Model'!B13*B22*'rNPV Model'!B16*'rNPV Model'!B18*((1-(1+F22)^(-'rNPV Model'!B47))/F22)/(1+F22)^('rNPV Model'!B8-'rNPV Model'!B10)*C22)+('rNPV Model'!B60*((1-(1+F22)^(-'rNPV Model'!B57))/F22)/(1+F22)^('rNPV Model'!B9-'rNPV Model'!B10)*D22)+(('rNPV Model'!B67+'rNPV Model'!B68+'rNPV Model'!B69+'rNPV Model'!B70+'rNPV Model'!B71)/(1+F22)^2.5))+MAX(0,(('rNPV Model'!B13*B22*'rNPV Model'!B16*'rNPV Model'!B18*((1-(1+F22)^(-'rNPV Model'!B47))/F22)/(1+F22)^('rNPV Model'!B8-'rNPV Model'!B10)*C22)+('rNPV Model'!B60*((1-(1+F22)^(-'rNPV Model'!B57))/F22)/(1+F22)^('rNPV Model'!B9-'rNPV Model'!B10)*D22)+(('rNPV Model'!B67+'rNPV Model'!B68+'rNPV Model'!B69+'rNPV Model'!B70+'rNPV Model'!B71)/(1+F22)^2.5)))*$D$7+E22+'rNPV Model'!B85)*1000000/'rNPV Model'!B90 -> 3.5831421 | H22: Safe + Confirmed Tissue PK/PD (Target Engagement), but no downstream structural changes
A23: Strong (MoA) | B23: 0.07 | C23: 0.38 | D23: 0.3 | E23: 150 | F23: 0.12 | G23: =((('rNPV Model'!B13*B23*'rNPV Model'!B16*'rNPV Model'!B18*((1-(1+F23)^(-'rNPV Model'!B47))/F23)/(1+F23)^('rNPV Model'!B8-'rNPV Model'!B10)*C23)+('rNPV Model'!B60*((1-(1+F23)^(-'rNPV Model'!B57))/F23)/(1+F23)^('rNPV Model'!B9-'rNPV Model'!B10)*D23)+(('rNPV Model'!B67+'rNPV Model'!B68+'rNPV Model'!B69+'rNPV Model'!B70+'rNPV Model'!B71)/(1+F23)^2.5))+MAX(0,(('rNPV Model'!B13*B23*'rNPV Model'!B16*'rNPV Model'!B18*((1-(1+F23)^(-'rNPV Model'!B47))/F23)/(1+F23)^('rNPV Model'!B8-'rNPV Model'!B10)*C23)+('rNPV Model'!B60*((1-(1+F23)^(-'rNPV Model'!B57))/F23)/(1+F23)^('rNPV Model'!B9-'rNPV Model'!B10)*D23)+(('rNPV Model'!B67+'rNPV Model'!B68+'rNPV Model'!B69+'rNPV Model'!B70+'rNPV Model'!B71)/(1+F23)^2.5)))*$D$7+E23+'rNPV Model'!B85)*1000000/'rNPV Model'!B90 -> 5.2974104 | H23: Significant reduction in Fibrosis Genes (scRNA-seq) and/or resolution of Inflammatory Edema (precursor to stricture improvement)
A24: Blue Sky | B24: 0.1 | C24: 0.38 | D24: 0.3 | E24: 250 | F24: 0.1 | G24: =((('rNPV Model'!B13*B24*'rNPV Model'!B16*'rNPV Model'!B18*((1-(1+F24)^(-'rNPV Model'!B47))/F24)/(1+F24)^('rNPV Model'!B8-'rNPV Model'!B10)*C24)+('rNPV Model'!B60*((1-(1+F24)^(-'rNPV Model'!B57))/F24)/(1+F24)^('rNPV Model'!B9-'rNPV Model'!B10)*D24)+(('rNPV Model'!B67+'rNPV Model'!B68+'rNPV Model'!B69+'rNPV Model'!B70+'rNPV Model'!B71)/(1+F24)^2.5))+MAX(0,(('rNPV Model'!B13*B24*'rNPV Model'!B16*'rNPV Model'!B18*((1-(1+F24)^(-'rNPV Model'!B47))/F24)/(1+F24)^('rNPV Model'!B8-'rNPV Model'!B10)*C24)+('rNPV Model'!B60*((1-(1+F24)^(-'rNPV Model'!B57))/F24)/(1+F24)^('rNPV Model'!B9-'rNPV Model'!B10)*D24)+(('rNPV Model'!B67+'rNPV Model'!B68+'rNPV Model'!B69+'rNPV Model'!B70+'rNPV Model'!B71)/(1+F24)^2.5)))*$D$7+E24+'rNPV Model'!B85)*1000000/'rNPV Model'!B90 -> 7.14374 | H24: M&A/BO
A26: KEY ASSUMPTION JUSTIFICATIONS
A27: UC cPoS 28%: 100% clinical response in Ph1b is top-decile. Apremilast (PDE4) approval validates class.
A28: FSCD cPoS 18%: PDE4B antifibrotic validated by BI 1015550 in IPF (NEJM). Agomab STENOVA de-risks path.
A29: FSCD $2.25B peak: 250K US patients, $40K/yr orphan-adjacent pricing, 15% penetration, 0.5x ROW.
A30: UC 6% share: Oral gut-targeted, no systemic immunosuppression vs JAK/biologics. Convenience advantage.
A31: Competitor: Agomab ontunisertib (ALK5) Ph2a+; different MOA. Spesolimab (BI) FAILED in FSCD.
